[
    {
      "title": "qwert",
      "first_name": "krishan",
      "last_name": "p",
      "known_as": "asdfg",
      "sex": "male",
      "date_of_birth": "12/07/1998",
      "age_next": "23",
      "relation_to_client": "qw",
      "parent": "sfd",
      "smoker": "efdsfer",
      "living_at_home": "df",
      "financially_dependant": "we",
      "note": "wer"
    },
    {
        "title": "qwe",
        "first_name": "arathi",
        "last_name": "p",
        "known_as": "asdfg",
        "sex": "male",
        "date_of_birth": "12/07/1998",
        "age_next": "23",
        "relation_to_client": "qw",
        "parent": "sfd",
        "smoker": "efdsfer",
        "living_at_home": "df",
        "financially_dependant": "we",
        "note": "wer"
      },
      {
        "title": "qwert",
        "first_name": "karthika",
        "last_name": "p",
        "known_as": "asdfg",
        "sex": "male",
        "date_of_birth": "12/07/1998",
        "age_next": "23",
        "relation_to_client": "qw",
        "parent": "sfd",
        "smoker": "efdsfer",
        "living_at_home": "df",
        "financially_dependant": "we",
        "note": "wer"
      },
      {
        "title": "qwert",
        "first_name": "arun",
        "last_name": "p",
        "known_as": "asdfg",
        "sex": "male",
        "date_of_birth": "12/07/1998",
        "age_next": "23",
        "relation_to_client": "qw",
        "parent": "sfd",
        "smoker": "efdsfer",
        "living_at_home": "df",
        "financially_dependant": "we",
        "note": "wer"
      }
  ]